geo_rasterize-0.9.0.dist-info/METADATA
geo_rasterize-0.9.0.dist-info/WHEEL
geo_rasterize-0.9.0.dist-info/license_files/LICENSE-APACHE
geo_rasterize/__init__.py
geo_rasterize/__init__.pyi
geo_rasterize/py.typed
geo_rasterize/geo_rasterize.pyd
geo_rasterize-0.9.0.dist-info/RECORD
