Metadata-Version: 2.1
Name: geo-rasterize
Version: 0.9.0
Classifier: Programming Language :: Rust
Classifier: Programming Language :: Python :: Implementation :: CPython
Classifier: Programming Language :: Python :: Implementation :: PyPy
Classifier: Development Status :: 4 - Beta
Classifier: Topic :: Multimedia :: Graphics
Classifier: Topic :: Scientific/Engineering :: GIS
Classifier: Topic :: Scientific/Engineering :: Image Processing
Classifier: Topic :: Scientific/Engineering :: Visualization
Classifier: Programming Language :: Python :: 3.7
Classifier: Programming Language :: Python :: 3.8
Classifier: Programming Language :: Python :: 3.9
Classifier: Programming Language :: Python :: 3.10
Classifier: Programming Language :: Python :: 3.11
Requires-Dist: numpy>=1.16
Requires-Dist: shapely>=1.6
License-File: LICENSE-APACHE
Summary: a 2D rasterizer for geospatial applications, written in Rust
Keywords: geospatial,gis,geo,raster,geographic
Author-email: Michael Salib <msalib@gmail.com>
Requires-Python: >=3.7
